{
    "pools": [
        {
            "rolls": 1,
            "entries": [
                {
                    "type": "minecraft:item",
                    "name": "minecraft:shield",
                    "functions": [
                        {
                            "function": "minecraft:set_nbt",
                            "tag": "{ttb:{item:'deadlock_shield'},display:{Name:'{\"translate\":\"item.ttb.deadlock_shield\",\"italic\":false,\"color\":\"green\"}'},BlockEntityTag:{Base:5,Patterns:[{Pattern:'dls',Color:13},{Pattern:'flo',Color:9},{Pattern:'mr',Color:13}]},CustomModelData:6830001}"
                        }
                    ]
                }
            ]
        }
    ]
}
