{
    "pools": [
        {
            "rolls": 1,
            "entries": [
                {
                    "type": "minecraft:loot_table",
                    "name": "ttb:items/template/base",
                    "functions": [
                        {
                            "function": "minecraft:set_nbt",
                            "tag": "{ttb:{item:'tempite_gel',tempite_energy:{amount:100,unstable:1b}},display:{Name:'{\"translate\":\"item.ttb.tempite_gel\",\"italic\":false}',Lore:['{\"translate\":\"item.ttb.tempite_gel.lore.0\"}']},CustomModelData:6830004}"
                        }
                    ]
                }
            ]
        }
    ]
}
